parserheader/__init__.py
parserheader/__version__.py
parserheader/parserheader.py
parserheader-0.38.3.data/data/LICENSE
parserheader-0.38.3.data/data/README.md
parserheader-0.38.3.data/data/__version__.py
parserheader-0.38.3.dist-info/METADATA
parserheader-0.38.3.dist-info/WHEEL
parserheader-0.38.3.dist-info/top_level.txt
parserheader-0.38.3.dist-info/RECORD
