Metadata-Version: 2.4
Name: parserheader
Version: 0.38.3
Summary: Parsing headers from string or dictionary
Home-page: https://github.com/cumulus13/parserheader
Author: Hadi Cahyadi LD
Author-email: cumulus13@gmail.com
Maintainer: cumulus13 Team
Maintainer-email: cumulus13@gmail.com
License: BSD
Project-URL: Documentation, https://github.com/cumulus13/parserheader
Project-URL: Code, https://github.com/cumulus13/parserheader
Classifier: Development Status :: 5 - Production/Stable
Classifier: Intended Audience :: Developers
Classifier: License :: OSI Approved :: BSD License
Classifier: Operating System :: OS Independent
Classifier: Programming Language :: Python
Classifier: Programming Language :: Python :: 2
Classifier: Programming Language :: Python :: 2.7
Classifier: Programming Language :: Python :: 3
Classifier: Programming Language :: Python :: 3.4
Classifier: Programming Language :: Python :: 3.5
Classifier: Programming Language :: Python :: 3.6
Classifier: Programming Language :: Python :: 3.7
Requires-Python: >=2.7, !=3.0.*, !=3.1.*, !=3.2.*, !=3.3.*
Requires-Dist: click
Dynamic: author
Dynamic: author-email
Dynamic: classifier
Dynamic: description
Dynamic: description-content-type
Dynamic: home-page
Dynamic: license
Dynamic: maintainer
Dynamic: maintainer-email
Dynamic: project-url
Dynamic: requires-dist
Dynamic: requires-python
Dynamic: summary
